NLP_LIB/__init__.py
NLP_LIB/__main__.py
NLP_LIB/benchmark_enwiki_small_lm_tfbase_enc_s2s_sp_bertlr.json
NLP_LIB/core.py
NLP_LIB/finetune_best2010lm_tfbase12_dec_s2s_best2010.json
NLP_LIB/finetune_best2010lm_tfbase12_dec_s2s_sp_best2010.json
NLP_LIB/finetune_best2010lm_tfbase12_dec_s2s_sp_truevoice.json
NLP_LIB/finetune_best2010lm_tfbase12_dec_s2s_sp_wisesight.json
NLP_LIB/finetune_best2010lm_tfbase12_dec_s2s_sp_wongnai.json
NLP_LIB/finetune_best2010lm_tfbase12_dec_s2s_truevoice.json
NLP_LIB/finetune_best2010lm_tfbase12_dec_s2s_wisesight.json
NLP_LIB/finetune_best2010lm_tfbase12_dec_s2s_wongnai.json
NLP_LIB/finetune_best2010lm_tfbase12_enc_s2s_best2010.json
NLP_LIB/finetune_best2010lm_tfbase12_enc_s2s_sp_best2010.json
NLP_LIB/finetune_best2010lm_tfbase12_enc_s2s_sp_truevoice.json
NLP_LIB/finetune_best2010lm_tfbase12_enc_s2s_sp_wisesight.json
NLP_LIB/finetune_best2010lm_tfbase12_enc_s2s_sp_wongnai.json
NLP_LIB/finetune_best2010lm_tfbase12_enc_s2s_truevoice.json
NLP_LIB/finetune_best2010lm_tfbase12_enc_s2s_wisesight.json
NLP_LIB/finetune_best2010lm_tfbase12_enc_s2s_wongnai.json
NLP_LIB/finetune_best2010lm_tfbase2_dec_s2s_best2010.json
NLP_LIB/finetune_best2010lm_tfbase2_dec_s2s_sp_best2010.json
NLP_LIB/finetune_best2010lm_tfbase2_dec_s2s_truevoice.json
NLP_LIB/finetune_best2010lm_tfbase2_dec_s2s_wisesight.json
NLP_LIB/finetune_best2010lm_tfbase2_dec_s2s_wongnai.json
NLP_LIB/finetune_best2010lm_tfbase2_enc_s2s_best2010.json
NLP_LIB/finetune_best2010lm_tfbase2_enc_s2s_truevoice.json
NLP_LIB/finetune_best2010lm_tfbase2_enc_s2s_wisesight.json
NLP_LIB/finetune_best2010lm_tfbase2_enc_s2s_wongnai.json
NLP_LIB/finetune_best2010lm_tfbase4_dec_s2s_best2010.json
NLP_LIB/finetune_best2010lm_tfbase4_dec_s2s_truevoice.json
NLP_LIB/finetune_best2010lm_tfbase4_dec_s2s_wisesight.json
NLP_LIB/finetune_best2010lm_tfbase4_dec_s2s_wongnai.json
NLP_LIB/finetune_best2010lm_tfbase4_enc_s2s_best2010.json
NLP_LIB/finetune_best2010lm_tfbase4_enc_s2s_truevoice.json
NLP_LIB_cpu-0.0.12.dist-info/LICENSE
NLP_LIB_cpu-0.0.12.dist-info/METADATA
NLP_LIB_cpu-0.0.12.dist-info/WHEEL
NLP_LIB_cpu-0.0.12.dist-info/top_level.txt
NLP_LIB_cpu-0.0.12.dist-info/RECORD
