Metadata-Version: 2.1
Name: NLP-LIB-cpu
Version: 0.0.12
Summary: Python library for Language Model / Finetune using Transformer based models.
Home-page: https://github.com/twilightdema/NLP_LIB.git
Author: Chulayuth Asawaroengchai
Author-email: twilightdema@gmail.com
License: UNKNOWN
Platform: UNKNOWN
Classifier: Programming Language :: Python :: 3
Classifier: License :: OSI Approved :: MIT License
Classifier: Operating System :: OS Independent
Requires-Python: >=3.6
Requires-Dist: absl-py (==0.9.0)
Requires-Dist: astor (==0.8.1)
Requires-Dist: Flask (==1.1.1)
Requires-Dist: gast (==0.3.2)
Requires-Dist: google-pasta (==0.1.8)
Requires-Dist: grpcio (==1.26.0)
Requires-Dist: h5py (==2.10.0)
Requires-Dist: Keras (==2.3.1)
Requires-Dist: Keras-Applications (==1.0.8)
Requires-Dist: Keras-Preprocessing (==1.1.0)
Requires-Dist: Markdown (==3.1.1)
Requires-Dist: numpy (==1.18.0)
Requires-Dist: protobuf (==3.11.2)
Requires-Dist: PyYAML (==5.2)
Requires-Dist: scipy (==1.4.1)
Requires-Dist: sentencepiece (==0.1.85)
Requires-Dist: six (==1.13.0)
Requires-Dist: tensorboard (==1.14.0)
Requires-Dist: tensorflow (==1.14.0)
Requires-Dist: tensorflow-estimator (==1.14.0)
Requires-Dist: termcolor (==1.1.0)
Requires-Dist: Werkzeug (==0.16.0)
Requires-Dist: wrapt (==1.11.2)
